mtrain_superclient/__init__.py
mtrain_superclient/__main__.py
mtrain_superclient/autoconfig.py
mtrain_superclient/client.py
mtrain_superclient/exceptions.py
mtrain_superclient/github_regimens.py
mtrain_superclient/models.py
mtrain_superclient/mtrain_lims.py
mtrain_superclient/mtrain_lims_upload.sh
mtrain_superclient/py.typed
mtrain_superclient/utils.py
mtrain_superclient-0.13.0.dist-info/entry_points.txt
mtrain_superclient-0.13.0.dist-info/LICENSE
mtrain_superclient-0.13.0.dist-info/WHEEL
mtrain_superclient-0.13.0.dist-info/METADATA
mtrain_superclient-0.13.0.dist-info/RECORD
