Metadata-Version: 2.1
Name: mtrain-superclient
Version: 0.13.0
Summary: Mtrain Superclient
Home-page: https://github.com/mochic/mtrain-superclient
License: MIT
Author: Christopher Mochizuki
Author-email: chrism@alleninstitute.org
Requires-Python: >=3.7,<4.0
Classifier: Development Status :: 1 - Planning
Classifier: License :: OSI Approved :: MIT License
Classifier: Programming Language :: Python :: 3
Classifier: Programming Language :: Python :: 3.10
Classifier: Programming Language :: Python :: 3.7
Classifier: Programming Language :: Python :: 3.8
Classifier: Programming Language :: Python :: 3.9
Requires-Dist: PyGithub (>=1.59.0,<2.0.0)
Requires-Dist: click (>=8.0.1)
Requires-Dist: np-config (>=0.4.25,<0.5.0)
Requires-Dist: pydantic (>=2.0,<3.0)
Requires-Dist: pytest (>=7.2.1,<8.0.0)
Requires-Dist: requests (>=2.31.0,<3.0.0)
Requires-Dist: ruamel.yaml (>=0.17.32,<0.18.0)
Requires-Dist: ruamel.yaml.string (>=0.1.1,<0.2.0)
Project-URL: Changelog, https://github.com/mochic/mtrain-superclient/releases
Project-URL: Documentation, https://mtrain-superclient.readthedocs.io
Project-URL: Repository, https://github.com/mochic/mtrain-superclient
